CS203_project_design_final.v
// Code your design here
`timescale 1ns / 1ps
module parking_system( 
 input clk, reset_n,
 input sensor_entrance, sensor_exit, 
 input[1:0] password,
 output wire GREEN_LED, RED_LED, 
 output reg[2:0] state,
 output reg[3:0] number,
 output reg[9:0] fare
 );
 parameter IDLE = 3'b000, WAIT_PASSWORD=3'b001, WRONG_PASS=3'b010, RIGHT_PASS=3'b011, STOP = 3'b100;
 reg[2:0] current_state, next_state;
 //reg[31:0] counter_wait;
 reg red_tmp,green_tmp;
  
  initial begin
   current_state = IDLE;
   number=4'b0000;
   fare=10'b0000000000;
  end

  always @(posedge clk or posedge reset_n)
   begin
    if(reset_n)
     begin
      current_state = IDLE;
      number=4'b0000;
      fare=10'b0000000000;
     end
    else
     begin
      current_state = next_state;      
     end
   end
 
  /*always @(posedge clk or posedge reset_n) 
   begin
    if(reset_n) 
     counter_wait <= 0;
    else if(current_state==WAIT_PASSWORD)
     counter_wait <= counter_wait + 1;
    else 
     counter_wait <= 0;
   end*/
 
 //State Interconnections...
 always @(*)
   begin
    case(current_state)
     IDLE: 
       begin
        if(sensor_entrance==1 && sensor_exit==1)
 		 next_state = STOP;
   		else if(sensor_entrance==1)
 		 next_state = WAIT_PASSWORD;
   		else
     	 next_state = IDLE;
 	   end
     WAIT_PASSWORD: 
       begin
 		//if(counter_wait <= 3)
 		 //next_state = WAIT_PASSWORD;
 		//else 
 	    // begin
          if((password==2'b11))
		   next_state = RIGHT_PASS;
		  else
		   next_state = WRONG_PASS;
	     //end
	   end
 	 WRONG_PASS: 
       begin
        if(password==2'b11)
 		 next_state = RIGHT_PASS;
 		else
		 next_state = WRONG_PASS;
	   end
     RIGHT_PASS: 
       begin
		if(sensor_entrance==1 && sensor_exit==1)
		 next_state = STOP;
		else if(sensor_exit==1)
		 next_state = IDLE;
		else
		 next_state = RIGHT_PASS;
		end
     STOP: 
       begin
		 if(sensor_entrance==1 && sensor_exit==1)
		  next_state = STOP;
		 else
 		  next_state = WAIT_PASSWORD;
 	   end
     default: next_state = IDLE;
    endcase
   end
 
 //Description of States
 always @(posedge clk) 
   begin 
     case(current_state)
 	 IDLE: 
     begin
 	  green_tmp = 1'b0;
 	  red_tmp = 1'b0;
 	  state = 3'b000; 
       fare = fare + (number*(4'b1010));
     end
     WAIT_PASSWORD: 
     begin
	  green_tmp = 1'b0;
	  red_tmp = 1'b1;
	  state = 3'b001;
       fare = fare + (number*(4'b1010));
     end
	 WRONG_PASS: 
     begin
	  green_tmp = 1'b0;
	  red_tmp = ~red_tmp;
	  state = 3'b010;  
       fare = fare + (number*(4'b1010));
	 end
	 RIGHT_PASS: 
     begin
	  green_tmp = 1'b1;
	  red_tmp = 1'b0;
	  state = 3'b011;
      number = number+4'b0001;
       fare = fare + (number*(4'b1010));
	 end
     STOP: 
     begin
	  green_tmp = 1'b0;
	  red_tmp = 1'b1;
	  state = 3'b100; 
      fare = fare + (number*(4'b1010));
     end
   endcase
 end
 assign RED_LED = red_tmp;
 assign GREEN_LED = green_tmp;
  
endmodule

CS203_project_testbench_final.v
// Code your testbench here
// or browse Examples

`timescale 1ns / 1ps
module tb_parking_system();
  // Inputs
  reg clk;
  reg reset_n;
  reg sensor_entrance;
  reg sensor_exit;
  reg [1:0] password;

  // Outputs
  wire GREEN_LED;
  wire RED_LED;
  wire [3:0] number;
  wire [9:0] fare;
  wire [2:0] state;
  
  parking_system uut (
  .clk(clk), 
  .reset_n(reset_n), 
  .sensor_entrance(sensor_entrance), 
  .sensor_exit(sensor_exit), 
  .password(password),
  .GREEN_LED(GREEN_LED), 
  .RED_LED(RED_LED), 
  .number(number),
  .fare(fare),
  .state(state)
 );
  
  
 initial begin
 // Initialize Inputs
 
 clk=1'b0;
 reset_n = 0;
 sensor_entrance = 0;
 sensor_exit = 0;
 password = 2'b00;
 #10 clk=1'b1;
 #10;
   $display("Welcome to Smart Car Parking System.\n");
   $display("Note: Single bit port mean ON if 1 and OFF if 0");
   $display("\nINPUTS\nSensor-entrance: %b, Sensor-exit: %b    //Idle state",sensor_entrance, sensor_exit);
   $display("Password: %b  (Correct password=11)",password);
   $display("OUTPUTS\nRed Light: %b, Green Light: %b",RED_LED, GREEN_LED);
   
   $display("Number: %b(Binary), %d (Decimal) | Fare: %d(Decimal)",number,number,fare);
   if(state==3'b000)
     $display("State: IDLE\n");
   else if(state==3'b001)
     $display("State: WAIT PASSWORD\n");
   else if(state==3'b010)
     $display("State: WRONG PASSWORD\n");
   else if(state==3'b011)
     $display("State: RIGHT PASSWORD\n");
   else if(state==3'b100)
     $display("State: STOP\n");
 
 clk=1'b0;
 reset_n = 0;
 sensor_entrance = 1;
 sensor_exit = 0;
 password = 2'b00;
 #10 clk=1'b1;
 #10;
   $display("\nINPUTS\nSensor-entrance: %b, Sensor-exit: %b    //Car incoming. Red Light and ask for Password",sensor_entrance, sensor_exit);
   $display("Password: %b  (Correct password=11)",password);
   $display("OUTPUTS\nRed Light: %b, Green Light: %b",RED_LED, GREEN_LED);
   
   $display("Number: %b(Binary), %d (Decimal) | Fare: %d(Decimal)",number,number,fare);
   if(state==3'b000)
     $display("State: IDLE\n");
   else if(state==3'b001)
     $display("State: WAIT PASSWORD\n");
   else if(state==3'b010)
     $display("State: WRONG PASSWORD\n");
   else if(state==3'b011)
     $display("State: RIGHT PASSWORD\n");
   else if(state==3'b100)
     $display("State: STOP\n");
 
 clk=1'b0;  
 reset_n = 0;
 sensor_entrance = 1;
 sensor_exit = 0;
 password = 2'b00;
 #10 clk=1'b1;
 #10;
   $display("\nINPUTS\nSensor-entrance: %b, Sensor-exit: %b    //Wrong password. Ask again",sensor_entrance, sensor_exit);
   $display("Password: %b  (Correct password=11)",password);
   $display("OUTPUTS\nRed Light: %b, Green Light: %b",RED_LED, GREEN_LED);
   
   $display("Number: %b(Binary), %d (Decimal) | Fare: %d(Decimal)",number,number,fare);
   if(state==3'b000)
     $display("State: IDLE\n");
   else if(state==3'b001)
     $display("State: WAIT PASSWORD\n");
   else if(state==3'b010)
     $display("State: WRONG PASSWORD\n");
   else if(state==3'b011)
     $display("State: RIGHT PASSWORD\n");
   else if(state==3'b100)
     $display("State: STOP\n");
   
 clk=1'b0;
 reset_n = 0;
 sensor_entrance = 1;
 sensor_exit = 0;
 password = 2'b11;
 #10 clk=1'b1;
 #10;
   $display("\nINPUTS\nSensor-entrance: %b, Sensor-exit: %b    //Correct password. Green light and Number of cars increased.",sensor_entrance, sensor_exit);
   $display("Password: %b  (Correct password=11)",password);
   $display("OUTPUTS\nRed Light: %b, Green Light: %b",RED_LED, GREEN_LED);
   
   $display("Number: %b(Binary), %d (Decimal) | Fare: %d(Decimal)",number,number,fare);
   if(state==3'b000)
     $display("State: IDLE\n");
   else if(state==3'b001)
     $display("State: WAIT PASSWORD\n");
   else if(state==3'b010)
     $display("State: WRONG PASSWORD\n");
   else if(state==3'b011)
     $display("State: RIGHT PASSWORD\n");
   else if(state==3'b100)
     $display("State: STOP\n");
   
 clk=1'b0;
 reset_n = 0;
 sensor_entrance = 0;
 sensor_exit = 1;
 password = 2'b11;
 #10 clk=1'b1;
 #10;
   $display("\nINPUTS\nSensor-entrance: %b, Sensor-exit: %b",sensor_entrance, sensor_exit);
   $display("Password: %b  (Correct password=11)",password);
   $display("OUTPUTS\nRed Light: %b, Green Light: %b",RED_LED, GREEN_LED);
   
   $display("Number: %b(Binary), %d (Decimal) | Fare: %d(Decimal)",number,number,fare);
   if(state==3'b000)
     $display("State: IDLE\n");
   else if(state==3'b001)
     $display("State: WAIT PASSWORD\n");
   else if(state==3'b010)
     $display("State: WRONG PASSWORD\n");
   else if(state==3'b011)
     $display("State: RIGHT PASSWORD\n");
   else if(state==3'b100)
     $display("State: STOP\n");
     
 clk=1'b0;
 reset_n = 0;
 sensor_entrance = 1;
 sensor_exit = 0;
 password = 2'b00;
 #10 clk=1'b1;
 #10;
   $display("\nINPUTS\nSensor-entrance: %b, Sensor-exit: %b    //New Car incoming. Red light and ask for password.",sensor_entrance, sensor_exit);
   $display("Password: %b  (Correct password=11)",password);
   $display("OUTPUTS\nRed Light: %b, Green Light: %b",RED_LED, GREEN_LED);
   
   $display("Number: %b(Binary), %d (Decimal) | Fare: %d(Decimal)",number,number,fare);
   if(state==3'b000)
     $display("State: IDLE\n");
   else if(state==3'b001)
     $display("State: WAIT PASSWORD\n");  
   else if(state==3'b010)
     $display("State: WRONG PASSWORD\n");
   else if(state==3'b011)
     $display("State: RIGHT PASSWORD\n");
   else if(state==3'b100)
     $display("State: STOP\n");
 
 clk=1'b0;
 reset_n = 0;
 sensor_entrance = 1;
 sensor_exit = 0;
 password = 2'b11;
 #10 clk=1'b1;
 #10;
   $display("\nINPUTS\nSensor-entrance: %b, Sensor-exit: %b    //Correct Password. Green Light and Parked",sensor_entrance, sensor_exit);
   $display("Password: %b  (Correct password=11)",password);
   $display("OUTPUTS\nRed Light: %b, Green Light: %b",RED_LED, GREEN_LED);
   
   $display("Number: %b(Binary), %d (Decimal) | Fare: %d(Decimal)",number,number,fare);
   if(state==3'b000)
     $display("State: IDLE\n");
   else if(state==3'b001)
     $display("State: WAIT PASSWORD\n");
   else if(state==3'b010)
     $display("State: WRONG PASSWORD\n");
   else if(state==3'b011)
     $display("State: RIGHT PASSWORD\n");
   else if(state==3'b100)
     $display("State: STOP\n");
 
 clk=1'b0;  
 reset_n = 0;
 sensor_entrance = 1;
 sensor_exit = 1;
 password = 2'b00;
 #10 clk=1'b1;
 #10;
   $display("\nINPUTS\nSensor-entrance: %b, Sensor-exit: %b    //New car comes simultaneously. Stop it to avoid collision.",sensor_entrance, sensor_exit);
   $display("Password: %b  (Correct password=11)",password);
   $display("OUTPUTS\nRed Light: %b, Green Light: %b",RED_LED, GREEN_LED);
   
   $display("Number: %b(Binary), %d (Decimal) | Fare: %d(Decimal)",number,number,fare);
   if(state==3'b000)
     $display("State: IDLE\n");
   else if(state==3'b001)
     $display("State: WAIT PASSWORD\n");
   else if(state==3'b010)
     $display("State: WRONG PASSWORD\n");
   else if(state==3'b011)
     $display("State: RIGHT PASSWORD\n");
   else if(state==3'b100)
     $display("State: STOP\n");
   
 clk=1'b0;
 reset_n = 0;
 sensor_entrance = 1;
 sensor_exit = 1;
 password = 2'b00;
 #10 clk=1'b1;
 #10;
   $display("\nINPUTS\nSensor-entrance: %b, Sensor-exit: %b    //Still both sensors are 1 So New car still Stopped.",sensor_entrance, sensor_exit);
   $display("Password: %b  (Correct password=11)",password);
   $display("OUTPUTS\nRed Light: %b, Green Light: %b",RED_LED, GREEN_LED);
   
   $display("Number: %b(Binary), %d (Decimal) | Fare: %d(Decimal)",number,number,fare);
   if(state==3'b000)
     $display("State: IDLE\n");
   else if(state==3'b001)
     $display("State: WAIT PASSWORD\n");
   else if(state==3'b010)
     $display("State: WRONG PASSWORD\n");
   else if(state==3'b011)
     $display("State: RIGHT PASSWORD\n");
   else if(state==3'b100)
     $display("State: STOP\n");

 clk=1'b0;
 reset_n = 0;
 sensor_entrance = 1;
 sensor_exit = 0;
 password = 2'b00;
 #10 clk=1'b1;
 #10;
   $display("\nINPUTS\nSensor-entrance: %b, Sensor-exit: %b    //Finally, exit sensor=0 so ask new car for password.",sensor_entrance, sensor_exit);
   $display("Password: %b  (Correct password=11)",password);
   $display("OUTPUTS\nRed Light: %b, Green Light: %b",RED_LED, GREEN_LED);
   
   $display("Number: %b(Binary), %d (Decimal) | Fare: %d(Decimal)",number,number,fare);
   if(state==3'b000)
     $display("State: IDLE\n");
   else if(state==3'b001)
     $display("State: WAIT PASSWORD\n");
   else if(state==3'b010)
     $display("State: WRONG PASSWORD\n");
   else if(state==3'b011)
     $display("State: RIGHT PASSWORD\n");
   else if(state==3'b100)
     $display("State: STOP\n");
  
 clk=1'b0;
 reset_n = 0;
 sensor_entrance = 1;
 sensor_exit = 0;
 password = 2'b11;
 #10 clk=1'b1;
 #10;
   $display("\nINPUTS\nSensor-entrance: %b, Sensor-exit: %b    //Correct password. Green light. Parked.",sensor_entrance, sensor_exit);
   $display("Password: %b  (Correct password=11)",password);
   $display("OUTPUTS\nRed Light: %b, Green Light: %b",RED_LED, GREEN_LED);
   
   $display("Number: %b(Binary), %d(Decimal) | Fare: %d(Decimal)",number,number,fare);
   if(state==3'b000)
     $display("State: IDLE\n");
   else if(state==3'b001)
     $display("State: WAIT PASSWORD\n");
   else if(state==3'b010)
     $display("State: WRONG PASSWORD\n");
   else if(state==3'b011)
     $display("State: RIGHT PASSWORD\n");
   else if(state==3'b100)
     $display("State: STOP\n\n");
   
  clk=1'b0;
 reset_n = 1'b1;
 sensor_entrance = 0;
 sensor_exit = 0;
 password = 2'b00;
 #10 clk=1'b1;
 #10;
   $display("RESETTING");
   $display("\nINPUTS\nSensor-entrance: %b, Sensor-exit: %b",sensor_entrance, sensor_exit);
   $display("Password: %b  (Correct password=11)",password);
   $display("OUTPUTS\nRed Light: %b, Green Light: %b",RED_LED, GREEN_LED);
   
   $display("Number: %b(Binary), %d(Decimal) | Fare: %d(Decimal)",number,number,fare);
   if(state==3'b000)
     $display("State: IDLE\n");
   else if(state==3'b001)
     $display("State: WAIT PASSWORD\n");
   else if(state==3'b010)
     $display("State: WRONG PASSWORD\n");
   else if(state==3'b011)
     $display("State: RIGHT PASSWORD\n");
   else if(state==3'b100)
     $display("State: STOP\n");
   $display("Reset successfull. Do visit again :)");
 
 end
      
endmodule

output.vcd
$date
	Sun Nov 21 10:46:05 2021
$end
$version
	Icarus Verilog
$end
$timescale
	1ps
$end
$scope module tb_parking_system $end
$var wire 3 ! state [2:0] $end
$var wire 4 " number [3:0] $end
$var wire 10 # fare [9:0] $end
$var wire 1 $ RED_LED $end
$var wire 1 % GREEN_LED $end
$var reg 1 & clk $end
$var reg 2 ' password [1:0] $end
$var reg 1 ( reset_n $end
$var reg 1 ) sensor_entrance $end
$var reg 1 * sensor_exit $end
$scope module uut $end
$var wire 1 % GREEN_LED $end
$var wire 1 $ RED_LED $end
$var wire 1 & clk $end
$var wire 2 + password [1:0] $end
$var wire 1 ( reset_n $end
$var wire 1 ) sensor_entrance $end
$var wire 1 * sensor_exit $end
$var reg 3 , current_state [2:0] $end
$var reg 10 - fare [9:0] $end
$var reg 1 . green_tmp $end
$var reg 3 / next_state [2:0] $end
$var reg 4 0 number [3:0] $end
$var reg 1 1 red_tmp $end
$var reg 3 2 state [2:0] $end
$upscope $end
$upscope $end
$enddefinitions $end
#0
$dumpvars
bx 2
x1
b0 0
b0 /
x.
b0 -
b0 ,
b0 +
0*
0)
0(
b0 '
0&
x%
x$
b0 #
b0 "
bx !
$end
#10000
b0 !
b0 2
0$
01
0%
0.
1&
#20000
b1 /
1)
0&
#30000
b10 /
b1 !
b1 2
1$
11
b1 ,
1&
#40000
0&
#50000
b10 !
b10 2
0$
01
b10 ,
1&
#60000
b11 /
b11 '
b11 +
0&
#70000
b1010 #
b1010 -
b1 "
b1 0
b11 !
b11 2
1%
1.
b11 ,
1&
#80000
b0 /
1*
0)
0&
#90000
b10100 #
b10100 -
b0 !
b0 2
0%
0.
b0 ,
1&
#100000
b1 /
b0 '
b0 +
0*
1)
0&
#110000
b10 /
b11110 #
b11110 -
b1 !
b1 2
1$
11
b1 ,
1&
#120000
b11 /
b11 '
b11 +
0&
#130000
b110010 #
b110010 -
b10 "
b10 0
b11 !
b11 2
0$
01
1%
1.
b11 ,
1&
#140000
b100 /
b0 '
b0 +
1*
0&
#150000
b1000110 #
b1000110 -
b100 !
b100 2
1$
11
0%
0.
b100 ,
1&
#160000
0&
#170000
b1011010 #
b1011010 -
1&
#180000
b1 /
0*
0&
#190000
b10 /
b1101110 #
b1101110 -
b1 !
b1 2
b1 ,
1&
#200000
b11 /
b11 '
b11 +
0&
#210000
b10001100 #
b10001100 -
b11 "
b11 0
b11 !
b11 2
0$
01
1%
1.
b11 ,
1&
#220000
b0 /
b0 #
b0 -
b0 "
b0 0
b0 ,
b0 '
b0 +
0)
1(
0&
#230000
b0 !
b0 2
0%
0.
1&
